penitus/__init__.py
penitus/exceptions.py
penitus/main.py
src/penitus/__init__.py
src/penitus/exceptions.py
src/penitus/main.py
penitus-1.2.dist-info/LICENSE.txt
penitus-1.2.dist-info/METADATA
penitus-1.2.dist-info/WHEEL
penitus-1.2.dist-info/top_level.txt
penitus-1.2.dist-info/RECORD
